Workbook

Sheet Q10
A1: product_id | B1: name | C1: categories | D1: mrp | E1: selling_price | F1: discount_percent | G1: listing_count | H1: category_count | I1: weight_gms
A2: 1250 | B2: RRO Mozzarella Block Cheese | C2: Beverages | Dairy, Bread & Batter | D2: 295 | E2: 147 | F2: 50 | G2: 2 | H2: 2 | I2: 200
A3: 594 | B3: Chef's Basket Durum Wheat Penne Pasta | C3: Chocolates & Candies | Cooking Essentials | Ice Cream & Desserts | Munchies | Packaged Food | D3: 160 | E3: 80 | F3: 50 | G3: 5 | H3: 5 | I3: 500
A4: 2722 | B4: Dukes Waffy Chocolate Wafer Rolls | C4: Biscuits | D4: 150 | E4: 75 | F4: 50 | G4: 1 | H4: 1 | I4: 250
A5: 3720 | B5: Epigamia Fruit Yogurt Strawberry | C5: Health & Hygiene | D5: 40 | E5: 20 | F5: 50 | G5: 1 | H5: 1 | I5: 75
A6: 600 | B6: Sugarlite 50% Less Calories Sugar Pouch | C6: Cooking Essentials | Munchies | D6: 99 | E6: 59 | F6: 40 | G6: 2 | H6: 2 | I6: 500
A7: 2745 | B7: Britannia Good Day Cashew Cookies | C7: Biscuits | D7: 230 | E7: 172 | F7: 25 | G7: 1 | H7: 1 | I7: 1000
A8: 1729 | B8: Mother's Recipe Ginger And Garlic Paste | C8: Chocolates & Candies | Ice Cream & Desserts | Packaged Food | D8: 50 | E8: 38 | F8: 24 | G8: 3 | H8: 3 | I8: 200
A9: 2749 | B9: Open Secret Choco Almond Story Box | C9: Biscuits | D9: 105 | E9: 81 | F9: 22 | G9: 1 | H9: 1 | I9: 75
A10: 1241 | B10: The Whole Truth Peanut Butter - Unsweetened & Crunchy | C10: Beverages | Chocolates & Candies | Dairy, Bread & Batter | Ice Cream & Desserts | Packaged Food | D10: 185 | E10: 148 | F10: 20 | G10: 5 | H10: 5 | I10: 325
A11: 89 | B11: Beetroot | C11: Fruits & Vegetables | D11: 11 | E11: 9 | F11: 18 | G11: 1 | H11: 1 | I11: 250
A12: 1246 | B12: Suguna Vitamin D Egg | C12: Beverages | Dairy, Bread & Batter | Meats, Fish & Eggs | D12: 75 | E12: 62 | F12: 17 | G12: 3 | H12: 3 | I12: 348
A13: 2751 | B13: Sunfeast Dark Fantasy Bourbon Bliss | C13: Biscuits | D13: 35 | E13: 29 | F13: 17 | G13: 1 | H13: 1 | I13: 150
... A218: 568 | B218: Ching's Chow Mein Hakka Noodles Masala | C218: Chocolates & Candies | Cooking Essentials | Ice Cream & Desserts | Munchies | Packaged Food | D218: 10 | E218: 10 | F218: 0 | G218: 5 | H218: 5 | I218: 20

Sheet Dashboard
B1: Zepto Catalog Health Audit
B2: 3,732 product listings | PostgreSQL + Excel
B3: Listings -> Unique Products | E3: Unique Products | H3: Out-of-stock rate | K3: Stock value held by Class A
B4: =INDEX(tblQ01a[total_listings],1) -> 3729 | E4: =INDEX(tblQ01a[unique_products],1) -> 1800 | H4: =SUM(tblQ02[oos_listings])/SUM(tblQ02[listings]) -> 0.12148029 | K4: =SUMIFS(tblQ09c[pct_of_value],tblQ09c[abc_class],"A")/100 -> 0.7 | O4: ="Current weights: "&TEXT(Restock_Model!B3,"0%")&" discount, "&TEXT(Restock_Model!B4,"0%")&" price, "&TEXT(Restock_Model!B5,"0%")&" visibility" -> Current weights: 40% discount, 30% price, 30% visibility
O5: Top 10 restock priorities
O6: ='Top20'!A1 -> Rank | P6: ='Top20'!B1 -> Product | Q6: ='Top20'!C1 -> Price | R6: ='Top20'!D1 -> Discount% | S6: ='Top20'!E1 -> Score
O7: ='Top20'!A2 -> 1 | P7: ='Top20'!B2 -> Chef's Basket Durum Wheat Penne Pasta | Q7: ='Top20'!C2 -> 80 | R7: ='Top20'!D2 -> 50 | S7: ='Top20'!E2 -> 0.67830935
O8: ='Top20'!A3 -> 2 | P8: ='Top20'!B3 -> RRO Mozzarella Block Cheese | Q8: ='Top20'!C3 -> 147 | R8: ='Top20'!D3 -> 50 | S8: ='Top20'!E3 -> 0.53446043
O9: ='Top20'!A4 -> 3 | P9: ='Top20'!B4 -> The Whole Truth Peanut Butter - Unsweetened & Crunchy | Q9: ='Top20'!C4 -> 148 | R9: ='Top20'!D4 -> 20 | S9: ='Top20'!E4 -> 0.475
O10: ='Top20'!A5 -> 4 | P10: ='Top20'!B5 -> Dukes Waffy Chocolate Wafer Rolls | Q10: ='Top20'!C5 -> 75 | R10: ='Top20'!D5 -> 50 | S10: ='Top20'!E5 -> 0.43561151
O11: ='Top20'!A6 -> 5 | P11: ='Top20'!B6 -> Sugarlite 50% Less Calories Sugar Pouch | Q11: ='Top20'!C6 -> 59 | R11: ='Top20'!D6 -> 40 | S11: ='Top20'!E6 -> 0.40697842
O12: ='Top20'!A7 -> 6 | P12: ='Top20'!B7 -> Epigamia Fruit Yogurt Strawberry | Q12: ='Top20'!C7 -> 20 | R12: ='Top20'!D7 -> 50 | S12: ='Top20'!E7 -> 0.40593525
O13: ='Top20'!A8 -> 7 | P13: ='Top20'!B8 -> Godrej Yummiez Chicken Breakfast Salami | Q13: ='Top20'!C8 -> 143 | R13: ='Top20'!D8 -> 4 | S13: ='Top20'!E8 -> 0.40430216
O14: ='Top20'!A9 -> 8 | P14: ='Top20'!B9 -> Zorabian Chicken Kheema Parathas | Q14: ='Top20'!C9 -> 190 | R14: ='Top20'!D9 -> 0 | S14: ='Top20'!E9 -> 0.39766187
O15: ='Top20'!A10 -> 9 | P15: ='Top20'!B10 -> Sunfeast Pasta Treat Pack of Tomato Cheese | Q15: ='Top20'!C10 -> 23 | R15: ='Top20'!D10 -> 17 | S15: ='Top20'!E10 -> 0.38355396
O16: ='Top20'!A11 -> 10 | P16: ='Top20'!B11 -> Patanjali Cow's Ghee | Q16: ='Top20'!C11 -> 565 | R16: ='Top20'!D11 -> 0 | S16: ='Top20'!E11 -> 0.36
B40: Source: Zepto product listings (Kaggle). Quantity is capped at 6, so stock value is an index.

Sheet Q09c
A1: abc_class | B1: products | C1: pct_of_products | D1: stock_value | E1: pct_of_value
A2: A | B2: 531 | C2: 33.5 | D2: 740536 | E2: 70
A3: B | B3: 428 | C3: 27 | D3: 211759.6 | E3: 20
A4: C | B4: 624 | C4: 39.4 | D4: 106158 | E4: 10

Sheet Q09b
A1: product_id | B1: name | C1: selling_price | D1: available_quantity | E1: stock_value | F1: value_rank | G1: cumulative_pct | H1: abc_class
A2: 518 | B2: Borges Extra Light Olive Oil Bottle | C2: 1399 | D2: 6 | E2: 8394 | F2: 1 | G2: 0.8 | H2: A
A3: 364 | B3: Praakritik Natural Desi Gir Cow A2 Ghee | C3: 1305 | D3: 6 | E3: 7830 | F3: 2 | G3: 1.5 | H3: A
A4: 145 | B4: Saffola Gold (Jar) | C4: 1240 | D4: 6 | E4: 7440 | F4: 3 | G4: 2.2 | H4: A
A5: 122 | B5: Dhara Kachi Ghani Mustard Oil Jar | C5: 1143 | D5: 6 | E5: 6858 | F5: 4 | G5: 2.9 | H5: A
A6: 147 | B6: Fortune Rice Bran Health Oil (Jar) | C6: 1039 | D6: 6 | E6: 6234 | F6: 5 | G6: 3.5 | H6: A
A7: 225 | B7: Dhara Filtered Groundnut Oil (Jar) | C7: 1035 | D7: 6 | E7: 6210 | F7: 6 | G7: 4.1 | H7: A
A8: 115 | B8: Fortune Soyabean Oil | C8: 999 | D8: 6 | E8: 5994 | F8: 7 | G8: 4.6 | H8: A
A9: 119 | B9: Dhara Health Refined Sun Flower Oil Jar | C9: 984 | D9: 6 | E9: 5904 | F9: 8 | G9: 5.2 | H9: A
A10: 105 | B10: Fortune Sunlite Refined Sunflower (Jar) | C10: 925 | D10: 6 | E10: 5550 | F10: 9 | G10: 5.7 | H10: A
A11: 2997 | B11: Pampers Premium Care Pants - Medium | C11: 899 | D11: 6 | E11: 5394 | F11: 10 | G11: 6.2 | H11: A
A12: 3539 | B12: Ariel Matic Front Load Detergent Washing Powder | C12: 680 | D12: 6 | E12: 4080 | F12: 11 | G12: 6.6 | H12: A
A13: 1512 | B13: Nestle Nestle Nan Pro Follow-Up Formula | C13: 650 | D13: 6 | E13: 3900 | F13: 12 | G13: 7 | H13: A
... A1584: 1431 | B1584: Ching's Secret Tomato Instant Soup | C1584: 10 | D1584: 1 | E1584: 10 | F1584: 1583 | G1584: 100 | H1584: C

Sheet pivot Q8
A1: Row Labels | B1: Count of name
A2: Bigger pack cheaper | B2: 69
A3: Bigger pack costs MORE | B3: 29
A4: Same rate | B4: 3
A5: Grand Total | B5: 101

Sheet Restock_Model
A1: Restock Priority Model
A3: Discount weight | B3: 0.4
A4: price weight | B4: 0.3
A5: Visibility weight | B5: 0.3
A6: Total | B6: =SUM(B3:B5) -> 1
A9: product_id | B9: name | C9: categories | D9: mrp | E9: selling_price | F9: discount_percent | G9: listing_count | H9: category_count | I9: weight_gms | J9: Disc_N | K9: Price_N | L9: Vis_N | M9: Score | N9: Rank
A10: 1250 | B10: RRO Mozzarella Block Cheese | C10: Beverages | Dairy, Bread & Batter | D10: 295 | E10: 147 | F10: 50 | G10: 2 | H10: 2 | I10: 200 | J10: =(tblRestock[[#This Row],[discount_percent]]-MIN(tblRestock[discount_percent]))/(MAX(tblRestock[discount_percent])-MIN(tblRestock[discount_percent])) -> 1 | K10: =(tblRestock[[#This Row],[selling_price]]-MIN(tblRestock[selling_price]))/(MAX(tblRestock[selling_price])-MIN(tblRestock[selling_price])) -> 0.24820144 | L10: =(tblRestock[[#This Row],[listing_count]]-MIN(tblRestock[listing_count]))/(MAX(tblRestock[listing_count])-MIN(tblRestock[listing_count])) -> 0.2 | M10: =$B$3*tblRestock[[#This Row],[Disc_N]]+$B$4*tblRestock[[#This Row],[Price_N]]+$B$5*tblRestock[[#This Row],[Vis_N]] -> 0.53446043 | N10: =_xlfn.RANK.EQ(M10,$M$10:$M$226,0)+COUNTIFS($M$10:$M$226,M10,$A$10:$A$226,"<"&A10) -> 2
A11: 594 | B11: Chef's Basket Durum Wheat Penne Pasta | C11: Chocolates & Candies | Cooking Essentials | Ice Cream & Desserts | Munchies | Packaged Food | D11: 160 | E11: 80 | F11: 50 | G11: 5 | H11: 5 | I11: 500 | J11: =(tblRestock[[#This Row],[discount_percent]]-MIN(tblRestock[discount_percent]))/(MAX(tblRestock[discount_percent])-MIN(tblRestock[discount_percent])) -> 1 | K11: =(tblRestock[[#This Row],[selling_price]]-MIN(tblRestock[selling_price]))/(MAX(tblRestock[selling_price])-MIN(tblRestock[selling_price])) -> 0.12769784 | L11: =(tblRestock[[#This Row],[listing_count]]-MIN(tblRestock[listing_count]))/(MAX(tblRestock[listing_count])-MIN(tblRestock[listing_count])) -> 0.8 | M11: =$B$3*tblRestock[[#This Row],[Disc_N]]+$B$4*tblRestock[[#This Row],[Price_N]]+$B$5*tblRestock[[#This Row],[Vis_N]] -> 0.67830935 | N11: =_xlfn.RANK.EQ(M11,$M$10:$M$226,0)+COUNTIFS($M$10:$M$226,M11,$A$10:$A$226,"<"&A11) -> 1
A12: 2722 | B12: Dukes Waffy Chocolate Wafer Rolls | C12: Biscuits | D12: 150 | E12: 75 | F12: 50 | G12: 1 | H12: 1 | I12: 250 | J12: =(tblRestock[[#This Row],[discount_percent]]-MIN(tblRestock[discount_percent]))/(MAX(tblRestock[discount_percent])-MIN(tblRestock[discount_percent])) -> 1 | K12: =(tblRestock[[#This Row],[selling_price]]-MIN(tblRestock[selling_price]))/(MAX(tblRestock[selling_price])-MIN(tblRestock[selling_price])) -> 0.11870504 | L12: =(tblRestock[[#This Row],[listing_count]]-MIN(tblRestock[listing_count]))/(MAX(tblRestock[listing_count])-MIN(tblRestock[listing_count])) -> 0 | M12: =$B$3*tblRestock[[#This Row],[Disc_N]]+$B$4*tblRestock[[#This Row],[Price_N]]+$B$5*tblRestock[[#This Row],[Vis_N]] -> 0.43561151 | N12: =_xlfn.RANK.EQ(M12,$M$10:$M$226,0)+COUNTIFS($M$10:$M$226,M12,$A$10:$A$226,"<"&A12) -> 4
A13: 3720 | B13: Epigamia Fruit Yogurt Strawberry | C13: Health & Hygiene | D13: 40 | E13: 20 | F13: 50 | G13: 1 | H13: 1 | I13: 75 | J13: =(tblRestock[[#This Row],[discount_percent]]-MIN(tblRestock[discount_percent]))/(MAX(tblRestock[discount_percent])-MIN(tblRestock[discount_percent])) -> 1 | K13: =(tblRestock[[#This Row],[selling_price]]-MIN(tblRestock[selling_price]))/(MAX(tblRestock[selling_price])-MIN(tblRestock[selling_price])) -> 0.019784173 | L13: =(tblRestock[[#This Row],[listing_count]]-MIN(tblRestock[listing_count]))/(MAX(tblRestock[listing_count])-MIN(tblRestock[listing_count])) -> 0 | M13: =$B$3*tblRestock[[#This Row],[Disc_N]]+$B$4*tblRestock[[#This Row],[Price_N]]+$B$5*tblRestock[[#This Row],[Vis_N]] -> 0.40593525 | N13: =_xlfn.RANK.EQ(M13,$M$10:$M$226,0)+COUNTIFS($M$10:$M$226,M13,$A$10:$A$226,"<"&A13) -> 6
A14: 600 | B14: Sugarlite 50% Less Calories Sugar Pouch | C14: Cooking Essentials | Munchies | D14: 99 | E14: 59 | F14: 40 | G14: 2 | H14: 2 | I14: 500 | J14: =(tblRestock[[#This Row],[discount_percent]]-MIN(tblRestock[discount_percent]))/(MAX(tblRestock[discount_percent])-MIN(tblRestock[discount_percent])) -> 0.8 | K14: =(tblRestock[[#This Row],[selling_price]]-MIN(tblRestock[selling_price]))/(MAX(tblRestock[selling_price])-MIN(tblRestock[selling_price])) -> 0.089928058 | L14: =(tblRestock[[#This Row],[listing_count]]-MIN(tblRestock[listing_count]))/(MAX(tblRestock[listing_count])-MIN(tblRestock[listing_count])) -> 0.2 | M14: =$B$3*tblRestock[[#This Row],[Disc_N]]+$B$4*tblRestock[[#This Row],[Price_N]]+$B$5*tblRestock[[#This Row],[Vis_N]] -> 0.40697842 | N14: =_xlfn.RANK.EQ(M14,$M$10:$M$226,0)+COUNTIFS($M$10:$M$226,M14,$A$10:$A$226,"<"&A14) -> 5
A15: 2745 | B15: Britannia Good Day Cashew Cookies | C15: Biscuits | D15: 230 | E15: 172 | F15: 25 | G15: 1 | H15: 1 | I15: 1000 | J15: =(tblRestock[[#This Row],[discount_percent]]-MIN(tblRestock[discount_percent]))/(MAX(tblRestock[discount_percent])-MIN(tblRestock[discount_percent])) -> 0.5 | K15: =(tblRestock[[#This Row],[selling_price]]-MIN(tblRestock[selling_price]))/(MAX(tblRestock[selling_price])-MIN(tblRestock[selling_price])) -> 0.29316547 | L15: =(tblRestock[[#This Row],[listing_count]]-MIN(tblRestock[listing_count]))/(MAX(tblRestock[listing_count])-MIN(tblRestock[listing_count])) -> 0 | M15: =$B$3*tblRestock[[#This Row],[Disc_N]]+$B$4*tblRestock[[#This Row],[Price_N]]+$B$5*tblRestock[[#This Row],[Vis_N]] -> 0.28794964 | N15: =_xlfn.RANK.EQ(M15,$M$10:$M$226,0)+COUNTIFS($M$10:$M$226,M15,$A$10:$A$226,"<"&A15) -> 21
A16: 1729 | B16: Mother's Recipe Ginger And Garlic Paste | C16: Chocolates & Candies | Ice Cream & Desserts | Packaged Food | D16: 50 | E16: 38 | F16: 24 | G16: 3 | H16: 3 | I16: 200 | J16: =(tblRestock[[#This Row],[discount_percent]]-MIN(tblRestock[discount_percent]))/(MAX(tblRestock[discount_percent])-MIN(tblRestock[discount_percent])) -> 0.48 | K16: =(tblRestock[[#This Row],[selling_price]]-MIN(tblRestock[selling_price]))/(MAX(tblRestock[selling_price])-MIN(tblRestock[selling_price])) -> 0.052158273 | L16: =(tblRestock[[#This Row],[listing_count]]-MIN(tblRestock[listing_count]))/(MAX(tblRestock[listing_count])-MIN(tblRestock[listing_count])) -> 0.4 | M16: =$B$3*tblRestock[[#This Row],[Disc_N]]+$B$4*tblRestock[[#This Row],[Price_N]]+$B$5*tblRestock[[#This Row],[Vis_N]] -> 0.32764748 | N16: =_xlfn.RANK.EQ(M16,$M$10:$M$226,0)+COUNTIFS($M$10:$M$226,M16,$A$10:$A$226,"<"&A16) -> 13
A17: 2749 | B17: Open Secret Choco Almond Story Box | C17: Biscuits | D17: 105 | E17: 81 | F17: 22 | G17: 1 | H17: 1 | I17: 75 | J17: =(tblRestock[[#This Row],[discount_percent]]-MIN(tblRestock[discount_percent]))/(MAX(tblRestock[discount_percent])-MIN(tblRestock[discount_percent])) -> 0.44 | K17: =(tblRestock[[#This Row],[selling_price]]-MIN(tblRestock[selling_price]))/(MAX(tblRestock[selling_price])-MIN(tblRestock[selling_price])) -> 0.1294964 | L17: =(tblRestock[[#This Row],[listing_count]]-MIN(tblRestock[listing_count]))/(MAX(tblRestock[listing_count])-MIN(tblRestock[listing_count])) -> 0 | M17: =$B$3*tblRestock[[#This Row],[Disc_N]]+$B$4*tblRestock[[#This Row],[Price_N]]+$B$5*tblRestock[[#This Row],[Vis_N]] -> 0.21484892 | N17: =_xlfn.RANK.EQ(M17,$M$10:$M$226,0)+COUNTIFS($M$10:$M$226,M17,$A$10:$A$226,"<"&A17) -> 45
A18: 1241 | B18: The Whole Truth Peanut Butter - Unsweetened & Crunchy | C18: Beverages | Chocolates & Candies | Dairy, Bread & Batter | Ice Cream & Desserts | Packaged Food | D18: 185 | E18: 148 | F18: 20 | G18: 5 | H18: 5 | I18: 325 | J18: =(tblRestock[[#This Row],[discount_percent]]-MIN(tblRestock[discount_percent]))/(MAX(tblRestock[discount_percent])-MIN(tblRestock[discount_percent])) -> 0.4 | K18: =(tblRestock[[#This Row],[selling_price]]-MIN(tblRestock[selling_price]))/(MAX(tblRestock[selling_price])-MIN(tblRestock[selling_price])) -> 0.25 | L18: =(tblRestock[[#This Row],[listing_count]]-MIN(tblRestock[listing_count]))/(MAX(tblRestock[listing_count])-MIN(tblRestock[listing_count])) -> 0.8 | M18: =$B$3*tblRestock[[#This Row],[Disc_N]]+$B$4*tblRestock[[#This Row],[Price_N]]+$B$5*tblRestock[[#This Row],[Vis_N]] -> 0.475 | N18: =_xlfn.RANK.EQ(M18,$M$10:$M$226,0)+COUNTIFS($M$10:$M$226,M18,$A$10:$A$226,"<"&A18) -> 3
A19: 89 | B19: Beetroot | C19: Fruits & Vegetables | D19: 11 | E19: 9 | F19: 18 | G19: 1 | H19: 1 | I19: 250 | J19: =(tblRestock[[#This Row],[discount_percent]]-MIN(tblRestock[discount_percent]))/(MAX(tblRestock[discount_percent])-MIN(tblRestock[discount_percent])) -> 0.36 | K19: =(tblRestock[[#This Row],[selling_price]]-MIN(tblRestock[selling_price]))/(MAX(tblRestock[selling_price])-MIN(tblRestock[selling_price])) -> 0 | L19: =(tblRestock[[#This Row],[listing_count]]-MIN(tblRestock[listing_count]))/(MAX(tblRestock[listing_count])-MIN(tblRestock[listing_count])) -> 0 | M19: =$B$3*tblRestock[[#This Row],[Disc_N]]+$B$4*tblRestock[[#This Row],[Price_N]]+$B$5*tblRestock[[#This Row],[Vis_N]] -> 0.144 | N19: =_xlfn.RANK.EQ(M19,$M$10:$M$226,0)+COUNTIFS($M$10:$M$226,M19,$A$10:$A$226,"<"&A19) -> 105
A20: 1246 | B20: Suguna Vitamin D Egg | C20: Beverages | Dairy, Bread & Batter | Meats, Fish & Eggs | D20: 75 | E20: 62 | F20: 17 | G20: 3 | H20: 3 | I20: 348 | J20: =(tblRestock[[#This Row],[discount_percent]]-MIN(tblRestock[discount_percent]))/(MAX(tblRestock[discount_percent])-MIN(tblRestock[discount_percent])) -> 0.34 | K20: =(tblRestock[[#This Row],[selling_price]]-MIN(tblRestock[selling_price]))/(MAX(tblRestock[selling_price])-MIN(tblRestock[selling_price])) -> 0.095323741 | L20: =(tblRestock[[#This Row],[listing_count]]-MIN(tblRestock[listing_count]))/(MAX(tblRestock[listing_count])-MIN(tblRestock[listing_count])) -> 0.4 | M20: =$B$3*tblRestock[[#This Row],[Disc_N]]+$B$4*tblRestock[[#This Row],[Price_N]]+$B$5*tblRestock[[#This Row],[Vis_N]] -> 0.28459712 | N20: =_xlfn.RANK.EQ(M20,$M$10:$M$226,0)+COUNTIFS($M$10:$M$226,M20,$A$10:$A$226,"<"&A20) -> 23
A21: 2751 | B21: Sunfeast Dark Fantasy Bourbon Bliss | C21: Biscuits | D21: 35 | E21: 29 | F21: 17 | G21: 1 | H21: 1 | I21: 150 | J21: =(tblRestock[[#This Row],[discount_percent]]-MIN(tblRestock[discount_percent]))/(MAX(tblRestock[discount_percent])-MIN(tblRestock[discount_percent])) -> 0.34 | K21: =(tblRestock[[#This Row],[selling_price]]-MIN(tblRestock[selling_price]))/(MAX(tblRestock[selling_price])-MIN(tblRestock[selling_price])) -> 0.035971223 | L21: =(tblRestock[[#This Row],[listing_count]]-MIN(tblRestock[listing_count]))/(MAX(tblRestock[listing_count])-MIN(tblRestock[listing_count])) -> 0 | M21: =$B$3*tblRestock[[#This Row],[Disc_N]]+$B$4*tblRestock[[#This Row],[Price_N]]+$B$5*tblRestock[[#This Row],[Vis_N]] -> 0.14679137 | N21: =_xlfn.RANK.EQ(M21,$M$10:$M$226,0)+COUNTIFS($M$10:$M$226,M21,$A$10:$A$226,"<"&A21) -> 100
... A226: 568 | B226: Ching's Chow Mein Hakka Noodles Masala | C226: Chocolates & Candies | Cooking Essentials | Ice Cream & Desserts | Munchies | Packaged Food | D226: 10 | E226: 10 | F226: 0 | G226: 5 | H226: 5 | I226: 20 | J226: =(tblRestock[[#This Row],[discount_percent]]-MIN(tblRestock[discount_percent]))/(MAX(tblRestock[discount_percent])-MIN(tblRestock[discount_percent])) -> 0 | K226: =(tblRestock[[#This Row],[selling_price]]-MIN(tblRestock[selling_price]))/(MAX(tblRestock[selling_price])-MIN(tblRestock[selling_price])) -> 0.0017985612 | L226: =(tblRestock[[#This Row],[listing_count]]-MIN(tblRestock[listing_count]))/(MAX(tblRestock[listing_count])-MIN(tblRestock[listing_count])) -> 0.8 | M226: =$B$3*tblRestock[[#This Row],[Disc_N]]+$B$4*tblRestock[[#This Row],[Price_N]]+$B$5*tblRestock[[#This Row],[Vis_N]] -> 0.24053957 | N226: =_xlfn.RANK.EQ(M226,$M$10:$M$226,0)+COUNTIFS($M$10:$M$226,M226,$A$10:$A$226,"<"&A226) -> 36

Sheet Top20
A1: Rank | B1: Product | C1: Price | D1: Discount% | E1: Score | F1: product_id
A2: =ROWS($A$2:A2) -> 1 | B2: =INDEX(tblRestock[name],MATCH($A2,tblRestock[Rank],0)) -> Chef's Basket Durum Wheat Penne Pasta | C2: =INDEX(tblRestock[selling_price],MATCH($A2,tblRestock[Rank],0)) -> 80 | D2: =INDEX(tblRestock[discount_percent],MATCH($A2,tblRestock[Rank],0)) -> 50 | E2: =INDEX(tblRestock[Score],MATCH($A2,tblRestock[Rank],0)) -> 0.67830935 | F2: =INDEX(tblRestock[product_id],MATCH($A2,tblRestock[Rank],0)) -> 594
A3: =ROWS($A$2:A3) -> 2 | B3: =INDEX(tblRestock[name],MATCH($A3,tblRestock[Rank],0)) -> RRO Mozzarella Block Cheese | C3: =INDEX(tblRestock[selling_price],MATCH($A3,tblRestock[Rank],0)) -> 147 | D3: =INDEX(tblRestock[discount_percent],MATCH($A3,tblRestock[Rank],0)) -> 50 | E3: =INDEX(tblRestock[Score],MATCH($A3,tblRestock[Rank],0)) -> 0.53446043 | F3: =INDEX(tblRestock[product_id],MATCH($A3,tblRestock[Rank],0)) -> 1250
A4: =ROWS($A$2:A4) -> 3 | B4: =INDEX(tblRestock[name],MATCH($A4,tblRestock[Rank],0)) -> The Whole Truth Peanut Butter - Unsweetened & Crunchy | C4: =INDEX(tblRestock[selling_price],MATCH($A4,tblRestock[Rank],0)) -> 148 | D4: =INDEX(tblRestock[discount_percent],MATCH($A4,tblRestock[Rank],0)) -> 20 | E4: =INDEX(tblRestock[Score],MATCH($A4,tblRestock[Rank],0)) -> 0.475 | F4: =INDEX(tblRestock[product_id],MATCH($A4,tblRestock[Rank],0)) -> 1241
A5: =ROWS($A$2:A5) -> 4 | B5: =INDEX(tblRestock[name],MATCH($A5,tblRestock[Rank],0)) -> Dukes Waffy Chocolate Wafer Rolls | C5: =INDEX(tblRestock[selling_price],MATCH($A5,tblRestock[Rank],0)) -> 75 | D5: =INDEX(tblRestock[discount_percent],MATCH($A5,tblRestock[Rank],0)) -> 50 | E5: =INDEX(tblRestock[Score],MATCH($A5,tblRestock[Rank],0)) -> 0.43561151 | F5: =INDEX(tblRestock[product_id],MATCH($A5,tblRestock[Rank],0)) -> 2722
A6: =ROWS($A$2:A6) -> 5 | B6: =INDEX(tblRestock[name],MATCH($A6,tblRestock[Rank],0)) -> Sugarlite 50% Less Calories Sugar Pouch | C6: =INDEX(tblRestock[selling_price],MATCH($A6,tblRestock[Rank],0)) -> 59 | D6: =INDEX(tblRestock[discount_percent],MATCH($A6,tblRestock[Rank],0)) -> 40 | E6: =INDEX(tblRestock[Score],MATCH($A6,tblRestock[Rank],0)) -> 0.40697842 | F6: =INDEX(tblRestock[product_id],MATCH($A6,tblRestock[Rank],0)) -> 600
A7: =ROWS($A$2:A7) -> 6 | B7: =INDEX(tblRestock[name],MATCH($A7,tblRestock[Rank],0)) -> Epigamia Fruit Yogurt Strawberry | C7: =INDEX(tblRestock[selling_price],MATCH($A7,tblRestock[Rank],0)) -> 20 | D7: =INDEX(tblRestock[discount_percent],MATCH($A7,tblRestock[Rank],0)) -> 50 | E7: =INDEX(tblRestock[Score],MATCH($A7,tblRestock[Rank],0)) -> 0.40593525 | F7: =INDEX(tblRestock[product_id],MATCH($A7,tblRestock[Rank],0)) -> 3720
A8: =ROWS($A$2:A8) -> 7 | B8: =INDEX(tblRestock[name],MATCH($A8,tblRestock[Rank],0)) -> Godrej Yummiez Chicken Breakfast Salami | C8: =INDEX(tblRestock[selling_price],MATCH($A8,tblRestock[Rank],0)) -> 143 | D8: =INDEX(tblRestock[discount_percent],MATCH($A8,tblRestock[Rank],0)) -> 4 | E8: =INDEX(tblRestock[Score],MATCH($A8,tblRestock[Rank],0)) -> 0.40430216 | F8: =INDEX(tblRestock[product_id],MATCH($A8,tblRestock[Rank],0)) -> 606
A9: =ROWS($A$2:A9) -> 8 | B9: =INDEX(tblRestock[name],MATCH($A9,tblRestock[Rank],0)) -> Zorabian Chicken Kheema Parathas | C9: =INDEX(tblRestock[selling_price],MATCH($A9,tblRestock[Rank],0)) -> 190 | D9: =INDEX(tblRestock[discount_percent],MATCH($A9,tblRestock[Rank],0)) -> 0 | E9: =INDEX(tblRestock[Score],MATCH($A9,tblRestock[Rank],0)) -> 0.39766187 | F9: =INDEX(tblRestock[product_id],MATCH($A9,tblRestock[Rank],0)) -> 598
A10: =ROWS($A$2:A10) -> 9 | B10: =INDEX(tblRestock[name],MATCH($A10,tblRestock[Rank],0)) -> Sunfeast Pasta Treat Pack of Tomato Cheese | C10: =INDEX(tblRestock[selling_price],MATCH($A10,tblRestock[Rank],0)) -> 23 | D10: =INDEX(tblRestock[discount_percent],MATCH($A10,tblRestock[Rank],0)) -> 17 | E10: =INDEX(tblRestock[Score],MATCH($A10,tblRestock[Rank],0)) -> 0.38355396 | F10: =INDEX(tblRestock[product_id],MATCH($A10,tblRestock[Rank],0)) -> 599
A11: =ROWS($A$2:A11) -> 10 | B11: =INDEX(tblRestock[name],MATCH($A11,tblRestock[Rank],0)) -> Patanjali Cow's Ghee | C11: =INDEX(tblRestock[selling_price],MATCH($A11,tblRestock[Rank],0)) -> 565 | D11: =INDEX(tblRestock[discount_percent],MATCH($A11,tblRestock[Rank],0)) -> 0 | E11: =INDEX(tblRestock[Score],MATCH($A11,tblRestock[Rank],0)) -> 0.36 | F11: =INDEX(tblRestock[product_id],MATCH($A11,tblRestock[Rank],0)) -> 581
A12: =ROWS($A$2:A12) -> 11 | B12: =INDEX(tblRestock[name],MATCH($A12,tblRestock[Rank],0)) -> Top Ramen Masala | C12: =INDEX(tblRestock[selling_price],MATCH($A12,tblRestock[Rank],0)) -> 82 | D12: =INDEX(tblRestock[discount_percent],MATCH($A12,tblRestock[Rank],0)) -> 9 | E12: =INDEX(tblRestock[Score],MATCH($A12,tblRestock[Rank],0)) -> 0.35138849 | F12: =INDEX(tblRestock[product_id],MATCH($A12,tblRestock[Rank],0)) -> 590
A13: =ROWS($A$2:A13) -> 12 | B13: =INDEX(tblRestock[name],MATCH($A13,tblRestock[Rank],0)) -> Hershey's Cocoa + Almond Spread | C13: =INDEX(tblRestock[selling_price],MATCH($A13,tblRestock[Rank],0)) -> 266 | D13: =INDEX(tblRestock[discount_percent],MATCH($A13,tblRestock[Rank],0)) -> 9 | E13: =INDEX(tblRestock[Score],MATCH($A13,tblRestock[Rank],0)) -> 0.33066906 | F13: =INDEX(tblRestock[product_id],MATCH($A13,tblRestock[Rank],0)) -> 1760
... A21: =ROWS($A$2:A21) -> 20 | B21: =INDEX(tblRestock[name],MATCH($A21,tblRestock[Rank],0)) -> Ching's Secret Veg Hakka Noodles | C21: =INDEX(tblRestock[selling_price],MATCH($A21,tblRestock[Rank],0)) -> 107 | D21: =INDEX(tblRestock[discount_percent],MATCH($A21,tblRestock[Rank],0)) -> 0 | E21: =INDEX(tblRestock[Score],MATCH($A21,tblRestock[Rank],0)) -> 0.2928777 | F21: =INDEX(tblRestock[product_id],MATCH($A21,tblRestock[Rank],0)) -> 572

Sheet Sensitivity
A1: Rank | B1: Base | C1: Discount-heavy | D1: Price-heavy | E1: Visibility-heavy | F1: In how many lists | G1: Product
A2: 1 | B2: 594 | C2: 594 | D2: 581 | E2: 598 | F2: =COUNTIF($B$2:$E$11,B2) -> 3 | G2: =INDEX(tblRestock[name],MATCH(B2,tblRestock[product_id],0)) -> Chef's Basket Durum Wheat Penne Pasta
A3: 2 | B3: 1250 | C3: 1250 | D3: 3097 | E3: 606 | F3: =COUNTIF($B$2:$E$11,B3) -> 2 | G3: =INDEX(tblRestock[name],MATCH(B3,tblRestock[product_id],0)) -> RRO Mozzarella Block Cheese
A4: 3 | B4: 1241 | C4: 2722 | D4: 1760 | E4: 594 | F4: =COUNTIF($B$2:$E$11,B4) -> 3 | G4: =INDEX(tblRestock[name],MATCH(B4,tblRestock[product_id],0)) -> The Whole Truth Peanut Butter - Unsweetened & Crunchy
A5: 4 | B5: 2722 | C5: 3720 | D5: 554 | E5: 1241 | F5: =COUNTIF($B$2:$E$11,B5) -> 2 | G5: =INDEX(tblRestock[name],MATCH(B5,tblRestock[product_id],0)) -> Dukes Waffy Chocolate Wafer Rolls
A6: 5 | B6: 600 | C6: 600 | D6: 574 | E6: 599 | F6: =COUNTIF($B$2:$E$11,B6) -> 2 | G6: =INDEX(tblRestock[name],MATCH(B6,tblRestock[product_id],0)) -> Sugarlite 50% Less Calories Sugar Pouch
A7: 6 | B7: 3720 | C7: 1241 | D7: 546 | E7: 590 | F7: =COUNTIF($B$2:$E$11,B7) -> 2 | G7: =INDEX(tblRestock[name],MATCH(B7,tblRestock[product_id],0)) -> Epigamia Fruit Yogurt Strawberry
A8: 7 | B8: 606 | C8: 1729 | D8: 598 | E8: 1242 | F8: =COUNTIF($B$2:$E$11,B8) -> 2 | G8: =INDEX(tblRestock[name],MATCH(B8,tblRestock[product_id],0)) -> Godrej Yummiez Chicken Breakfast Salami
A9: 8 | B9: 598 | C9: 2745 | D9: 1745 | E9: 587 | F9: =COUNTIF($B$2:$E$11,B9) -> 3 | G9: =INDEX(tblRestock[name],MATCH(B9,tblRestock[product_id],0)) -> Zorabian Chicken Kheema Parathas
A10: 9 | B10: 599 | C10: 599 | D10: 1764 | E10: 572 | F10: =COUNTIF($B$2:$E$11,B10) -> 3 | G10: =INDEX(tblRestock[name],MATCH(B10,tblRestock[product_id],0)) -> Sunfeast Pasta Treat Pack of Tomato Cheese
A11: 10 | B11: 581 | C11: 2749 | D11: 1767 | E11: 1235 | F11: =COUNTIF($B$2:$E$11,B11) -> 2 | G11: =INDEX(tblRestock[name],MATCH(B11,tblRestock[product_id],0)) -> Patanjali Cow's Ghee

Sheet Q08
A1: name | B1: from_weight_g | C1: to_weight_g | D1: prev_price_per_100g | E1: price_per_100g | F1: change_pct | G1: verdict
A2: Godrej No.1 Bathing Soap – Lime & Aloe Vera | B2: 500 | C2: 600 | D2: 16.8 | E2: 24.83 | F2: 47.8 | G2: Bigger pack costs MORE
A3: Dove Daily Shine Shampoo | B3: 340 | C3: 650 | D3: 70.59 | E3: 94.15 | F3: 33.4 | G3: Bigger pack costs MORE
A4: Britannia Good Day Cashew Cookies | B4: 60 | C4: 100 | D4: 16.67 | E4: 20 | F4: 20 | G4: Bigger pack costs MORE
A5: Pillsbury Atta/Godihittu - Chakki Fresh | B5: 2000 | C5: 5000 | D5: 4.7 | E5: 5.5 | F5: 17 | G5: Bigger pack costs MORE
A6: Sunsilk Lusciously Thick & Long Shampoo | B6: 340 | C6: 650 | D6: 68.82 | E6: 80.15 | F6: 16.5 | G6: Bigger pack costs MORE
A7: Pantene Advanced Hair Fall Solution Shampoo - Total Damage Care | B7: 180 | C7: 340 | D7: 66.67 | E7: 77.65 | F7: 16.5 | G7: Bigger pack costs MORE
A8: Pedigree Puppy Dry Dog Food Food Chicken & Milk | B8: 1200 | C8: 3000 | D8: 19.33 | E8: 21.6 | F8: 11.7 | G8: Bigger pack costs MORE
A9: Lux International Creamy White Soap Bar | B9: 75 | C9: 125 | D9: 45.33 | E9: 50.4 | F9: 11.2 | G9: Bigger pack costs MORE
A10: Ariel Matic Top Load Detergent Washing Powder | B10: 1000 | C10: 2000 | D10: 22.5 | E10: 24.95 | F10: 10.9 | G10: Bigger pack costs MORE
A11: Fortune Soyabean Oil | B11: 1000 | C11: 5000 | D11: 18.1 | E11: 19.98 | F11: 10.4 | G11: Bigger pack costs MORE
A12: Britannia Good Day Pista Badam | B12: 100 | C12: 200 | D12: 20 | E12: 22 | F12: 10 | G12: Bigger pack costs MORE
A13: Smith & Jones Masala Noodles | B13: 360 | C13: 480 | D13: 16.94 | E13: 18.54 | F13: 9.4 | G13: Bigger pack costs MORE
... A102: Johnson's Baby Skincare Wipes | B102: 72 | C102: 1160 | D102: 306.94 | E102: 6.38 | F102: -97.9 | G102: Bigger pack cheaper

Sheet Q06
A1: name | B1: mrp | C1: selling_price | D1: discount_percent | E1: rupees_saved | F1: pct_rank | G1: rupee_rank | H1: rank_jump
A2: Borges Extra Light Olive Oil Bottle | B2: 2600 | C2: 1399 | D2: 46 | E2: 1201 | F2: 23 | G2: 1 | H2: 22
A3: Pampers Pants - Large | B3: 1549 | C3: 849 | D3: 45 | E3: 700 | F3: 24 | G3: 2 | H3: 22
A4: Kelloggs Chocos - Moons & Stars | B4: 660 | C4: 396 | D4: 40 | E4: 264 | F4: 27 | G4: 3 | H4: 24
A5: Pampers Active Baby Diapers New Born Extra Small | B5: 1099 | C5: 849 | D5: 22 | E5: 250 | F5: 81 | G5: 4 | H5: 77
A6: Popular Essentials Californian Almond | B6: 695 | C6: 470 | D6: 32 | E6: 225 | F6: 31 | G6: 5 | H6: 26
A7: Dhara Health Refined Sun Flower Oil Jar | B7: 1200 | C7: 984 | D7: 18 | E7: 216 | F7: 140 | G7: 6 | H7: 134
A8: Pampers Premium Care Pants - Large | B8: 1099 | C8: 899 | D8: 18 | E8: 200 | F8: 140 | G8: 7 | H8: 133
A9: Pampers Premium Care Pants - Medium | B9: 1099 | C9: 899 | D9: 18 | E9: 200 | F9: 140 | G9: 7 | H9: 133
A10: RRO Mascarpone Cheese | B10: 355 | C10: 177 | D10: 50 | E10: 178 | F10: 4 | G10: 9 | H10: -5
A11: Pampers Pants - Medium | B11: 699 | C11: 549 | D11: 21 | E11: 150 | F11: 90 | G11: 10 | H11: 80
A12: RRO Cheddar Block Cheese | B12: 295 | C12: 147 | D12: 50 | E12: 148 | F12: 4 | G12: 11 | H12: -7
A13: Praakritik Natural Desi Gir Cow A2 Ghee | B13: 1450 | C13: 1305 | D13: 10 | E13: 145 | F13: 386 | G13: 12 | H13: 374
... A26: Scotch Brite Multi-Purpose Sponge Wipes | B26: 700 | C26: 581 | D26: 17 | E26: 119 | F26: 152 | G26: 25 | H26: 127

Sheet Q05a
A1: price_band | B1: products | C1: avg_discount_pct | D1: median_discount_pct | E1: pct_with_no_discount
A2: 1. Under Rs100 | B2: 849 | C2: 6.5 | D2: 5 | E2: 34.3
A3: 2. Rs100-249 | B3: 652 | C3: 8 | D3: 6 | E3: 25.6
A4: 3. Rs250-499 | B4: 239 | C4: 11 | D4: 10 | E4: 24.3
A5: 4. Rs500-999 | B5: 47 | C5: 7.2 | D5: 5 | E5: 36.2
A6: 5. Rs1000+ | B6: 13 | C6: 14.4 | D6: 10 | E6: 23.1

Sheet Q04b
A1: category | B1: discount_band | C1: listings
A2: Beverages | B2: 1. No discount | C2: 47
A3: Beverages | B3: 2. 1-10% | C3: 58
A4: Beverages | B4: 3. 11-20% | C4: 12
A5: Beverages | B5: 4. 21-30% | C5: 2
A6: Beverages | B6: 5. Above 30% | C6: 10
A7: Biscuits | B7: 1. No discount | C7: 53
A8: Biscuits | B8: 2. 1-10% | C8: 57
A9: Biscuits | B9: 3. 11-20% | C9: 21
A10: Biscuits | B10: 4. 21-30% | C10: 11
A11: Biscuits | B11: 5. Above 30% | C11: 5
A12: Chocolates & Candies | B12: 1. No discount | C12: 132
A13: Chocolates & Candies | B13: 2. 1-10% | C13: 157
... A67: Personal Care | B67: 5. Above 30% | C67: 2

Sheet Q04a
A1: discount_band | B1: products | C1: pct_of_products
A2: 1. No discount | B2: 536 | C2: 29.8
A3: 2. 1-10% | B3: 852 | C3: 47.3
A4: 3. 11-20% | B4: 311 | C4: 17.3
A5: 4. 21-30% | B5: 64 | C5: 3.6
A6: 5. Above 30% | B6: 37 | C6: 2.1

Sheet Q02
A1: category | B1: listings | C1: oos_listings | D1: oos_pct | E1: pp_vs_overall | F1: worst_rank | G1: pct_cross_listed | H1: label_quality
A2: Biscuits | B2: 147 | C2: 42 | D2: 28.6 | E2: 16.4 | F2: 1 | G2: 0 | H2: Reliable label
A3: Beverages | B3: 129 | C3: 28 | D3: 21.7 | E3: 9.6 | F3: 2 | G3: 100 | H3: Heavily duplicated
A4: Dairy, Bread & Batter | B4: 129 | C4: 28 | D4: 21.7 | E4: 9.6 | F4: 2 | G4: 100 | H4: Heavily duplicated
A5: Meats, Fish & Eggs | B5: 63 | C5: 12 | D5: 19 | E5: 6.9 | F5: 4 | G5: 49.2 | H5: Mixed
A6: Health & Hygiene | B6: 97 | C6: 13 | D6: 13.4 | E6: 1.3 | F6: 5 | G6: 36.1 | H6: Mixed
A7: Munchies | B7: 514 | C7: 64 | D7: 12.5 | E7: 0.3 | F7: 6 | G7: 100 | H7: Heavily duplicated
A8: Cooking Essentials | B8: 514 | C8: 64 | D8: 12.5 | E8: 0.3 | F8: 6 | G8: 100 | H8: Heavily duplicated
A9: Ice Cream & Desserts | B9: 388 | C9: 45 | D9: 11.6 | E9: -0.6 | F9: 8 | G9: 100 | H9: Heavily duplicated
A10: Chocolates & Candies | B10: 388 | C10: 45 | D10: 11.6 | E10: -0.6 | F10: 8 | G10: 100 | H10: Heavily duplicated
A11: Packaged Food | B11: 388 | C11: 45 | D11: 11.6 | E11: -0.6 | F11: 8 | G11: 100 | H11: Heavily duplicated
A12: Home & Cleaning | B12: 193 | C12: 19 | D12: 9.8 | E12: -2.3 | F12: 11 | G12: 2.1 | H12: Reliable label
A13: Fruits & Vegetables | B13: 93 | C13: 6 | D13: 6.5 | E13: -5.7 | F13: 12 | G13: 4.3 | H13: Reliable label
... A15: Paan Corner | B15: 343 | C15: 21 | D15: 6.1 | E15: -6 | F15: 13 | G15: 100 | H15: Heavily duplicated

Sheet Sheet3

Sheet Q01a
A1: total_listings | B1: unique_products | C1: avg_listings_per_product | D1: products_in_multiple_categories | E1: pct_multi_category | F1: max_categories_one_product
A2: 3729 | B2: 1800 | C2: 2.07 | D2: 1281 | E2: 71.2 | F2: 7
